[
  {
    "commitId": "a461163716e9db60e66d10ba21ddedd6c998abf2",
    "commitShort": "a461163",
    "branch": "release/v2.0.0",
    "deployedAt": "2026-01-14T19:06:17Z",
    "commitMessage": "Short lived Sas"
  },
  {
    "commitId": "326c2042ce870b765c6dda9e1b5e335d3320bd3b",
    "commitShort": "326c204",
    "branch": "main",
    "deployedAt": "2026-01-14T15:00:01Z",
    "commitMessage": "Basic context encryption + Small UI fixes"
  },
  {
    "commitId": "b93a76ec86f582d28c84eac280de4d04023b8df8",
    "commitShort": "b93a76e",
    "branch": "main",
    "deployedAt": "2026-01-11T12:36:24Z",
    "commitMessage": "Removed unused variables"
  },
  {
    "commitId": "af3a9d25711364210441f093f491e9b1151f478d",
    "commitShort": "af3a9d2",
    "branch": "main",
    "deployedAt": "2026-01-11T11:36:57Z",
    "commitMessage": "Icon rearrangement"
  },
  {
    "commitId": "d10e06d55e8077a07cbd8ab75047fbfe260be548",
    "commitShort": "d10e06d",
    "branch": "main",
    "deployedAt": "2026-01-03T16:03:46Z",
    "commitMessage": "Redirect with query params fix"
  },
  {
    "commitId": "5ba19353d2874434676a17c8e7a400a756a24a98",
    "commitShort": "5ba1935",
    "branch": "main",
    "deployedAt": "2026-01-03T09:41:52Z",
    "commitMessage": "Remove console logs & alignment"
  },
  {
    "commitId": "480c7110271518aee8e99bda125a57076895b134",
    "commitShort": "480c711",
    "branch": "main",
    "deployedAt": "2026-01-03T08:39:54Z",
    "commitMessage": "Deployment changes"
  }
]
